multidirectional_graph/__init__.py
multidirectional_graph/_graph.py
multidirectional_graph/fonts/Oswald/Oswald-Bold.ttf
multidirectional_graph/fonts/Oswald/Oswald-ExtraLight.ttf
multidirectional_graph/fonts/Oswald/Oswald-Light.ttf
multidirectional_graph/fonts/Oswald/Oswald-Medium.ttf
multidirectional_graph/fonts/Oswald/Oswald-Regular.ttf
multidirectional_graph/fonts/Oswald/Oswald-SemiBold.ttf
multidirectional_graph/fonts/Oswald/Oswald-VariableFont_wght.ttf
multidirectional_graph/fonts/Roboto/LICENSE.txt
multidirectional_graph/fonts/Roboto/Roboto-Black.ttf
multidirectional_graph/fonts/Roboto/Roboto-BlackItalic.ttf
multidirectional_graph/fonts/Roboto/Roboto-Bold.ttf
multidirectional_graph/fonts/Roboto/Roboto-BoldItalic.ttf
multidirectional_graph/fonts/Roboto/Roboto-Italic.ttf
multidirectional_graph/fonts/Roboto/Roboto-Light.ttf
multidirectional_graph/fonts/Roboto/Roboto-LightItalic.ttf
multidirectional_graph/fonts/Roboto/Roboto-Medium.ttf
multidirectional_graph/fonts/Roboto/Roboto-MediumItalic.ttf
multidirectional_graph/fonts/Roboto/Roboto-Regular.ttf
multidirectional_graph/fonts/Roboto/Roboto-Thin.ttf
multidirectional_graph/fonts/Roboto/Roboto-ThinItalic.ttf
multidirectional_graph/fonts/SourceSerif/SourceSerifPro-Black.ttf
multidirectional_graph/fonts/SourceSerif/SourceSerifPro-BlackItalic.ttf
multidirectional_graph/fonts/SourceSerif/SourceSerifPro-Bold.ttf
multidirectional_graph/fonts/SourceSerif/SourceSerifPro-BoldItalic.ttf
multidirectional_graph/fonts/SourceSerif/SourceSerifPro-ExtraLight.ttf
multidirectional_graph/fonts/SourceSerif/SourceSerifPro-ExtraLightItalic.ttf
multidirectional_graph/fonts/SourceSerif/SourceSerifPro-Italic.ttf
multidirectional_graph/fonts/SourceSerif/SourceSerifPro-Light.ttf
multidirectional_graph/fonts/SourceSerif/SourceSerifPro-LightItalic.ttf
multidirectional_graph/fonts/SourceSerif/SourceSerifPro-Regular.ttf
multidirectional_graph/fonts/SourceSerif/SourceSerifPro-SemiBold.ttf
multidirectional_graph-0.1.7.dist-info/METADATA
multidirectional_graph-0.1.7.dist-info/WHEEL
multidirectional_graph-0.1.7.dist-info/top_level.txt
multidirectional_graph-0.1.7.dist-info/RECORD
