Metadata-Version: 2.1
Name: multidirectional-graph
Version: 0.1.7
Summary: Package for plotting multidirectional graphs
Author: Eduardo Messias de Morais
Author-email: emdemor415@gmail.com
Requires-Dist: matplotlib
